{"p": 0.1684, "rgb": "#8d96ae", "corr": 0.07283474834068554, "words": [{"color": "#d59dff", "text": "human", "initloc": {"y": 0, "x": 0}, "size": 2}, {"color": "#da46ff", "text": "indeed", "initloc": {"y": 0, "x": 0}, "size": 1}, {"color": "#fb5ad9", "text": "evidence", "initloc": {"y": 0, "x": 0}, "size": 1}, {"color": "#837cff", "text": "nature", "initloc": {"y": 0, "x": 0}, "size": 1}, {"color": "#de64ff", "text": "true", "initloc": {"y": 0, "x": 0}, "size": 1}, {"color": "#b193ff", "text": "humans", "initloc": {"y": 0, "x": 0}, "size": 1}, {"color": "#b861f9", "text": "beings", "initloc": {"y": 0, "x": 0}, "size": 1}, {"color": "#7a9cff", "text": "describe", "initloc": {"y": 0, "x": 0}, "size": 1}, {"color": "#ea5fff", "text": "belief", "initloc": {"y": 0, "x": 0}, "size": 1}, {"color": "#d35cfa", "text": "merely", "initloc": {"y": 0, "x": 0}, "size": 1}, {"color": "#7bcaff", "text": "sensitive", "initloc": {"y": 0, "x": 0}, "size": 1}, {"color": "#fb89ff", "text": "evil", "initloc": {"y": 0, "x": 0}, "size": 1}, {"color": "#a9bfff", "text": "weak", "initloc": {"y": 0, "x": 0}, "size": 1}, {"color": "#fc9fcd", "text": "disease", "initloc": {"y": 0, "x": 0}, "size": 1}, {"color": "#ff3aff", "text": "truth", "initloc": {"y": 0, "x": 0}, "size": 1}, {"color": "#8291ff", "text": "perception", "initloc": {"y": 0, "x": 0}, "size": 1}, {"color": "#ff61db", "text": "believed", "initloc": {"y": 0, "x": 0}, "size": 0}, {"color": "#d28bff", "text": "weakness", "initloc": {"y": 0, "x": 0}, "size": 0}, {"color": "#f67fd7", "text": "false", "initloc": {"y": 0, "x": 0}, "size": 0}, {"color": "#90dbed", "text": "substance", "initloc": {"y": 0, "x": 0}, "size": 0}], "cb": 0, "zyx": [13, 28, 71], "corr_r2l": 0.1997064675231132}