{"p": 0.8582, "rgb": "#6b848b", "corr": -0.06835354713978249, "words": [{"color": "#48aad9", "text": "itself", "initloc": {"y": 0, "x": 0}, "size": 0}, {"color": "#00ff8e", "text": "surface", "initloc": {"y": 0, "x": 0}, "size": 0}, {"color": "#7fb969", "text": "thus", "initloc": {"y": 0, "x": 0}, "size": 0}, {"color": "#00d4c4", "text": "flow", "initloc": {"y": 0, "x": 0}, "size": 0}, {"color": "#578a77", "text": "these", "initloc": {"y": 0, "x": 0}, "size": 0}, {"color": "#14cca7", "text": "create", "initloc": {"y": 0, "x": 0}, "size": 0}, {"color": "#0fff36", "text": "larger", "initloc": {"y": 0, "x": 0}, "size": 0}, {"color": "#62d17a", "text": "common", "initloc": {"y": 0, "x": 0}, "size": 0}, {"color": "#26ed80", "text": "sides", "initloc": {"y": 0, "x": 0}, "size": 0}, {"color": "#1ef685", "text": "soil", "initloc": {"y": 0, "x": 0}, "size": 0}, {"color": "#53e37c", "text": "quantity", "initloc": {"y": 0, "x": 0}, "size": 0}, {"color": "#36e994", "text": "types", "initloc": {"y": 0, "x": 0}, "size": 0}, {"color": "#0ad05b", "text": "above", "initloc": {"y": 0, "x": 0}, "size": 0}, {"color": "#38c758", "text": "higher", "initloc": {"y": 0, "x": 0}, "size": 0}, {"color": "#aac59c", "text": "prevent", "initloc": {"y": 0, "x": 0}, "size": 0}, {"color": "#00ff94", "text": "layer", "initloc": {"y": 0, "x": 0}, "size": 0}, {"color": "#57c0f8", "text": "effect", "initloc": {"y": 0, "x": 0}, "size": 0}, {"color": "#a3979c", "text": "therefore", "initloc": {"y": 0, "x": 0}, "size": 0}, {"color": "#43cd9e", "text": "method", "initloc": {"y": 0, "x": 0}, "size": 0}, {"color": "#40e381", "text": "reduce", "initloc": {"y": 0, "x": 0}, "size": 0}], "cb": 0, "zyx": [13, 59, 24], "corr_r2l": -0.027248544866023093}