{"p": 0.2597, "rgb": "#7594bb", "corr": 0.055573751935836885, "words": [{"color": "#72ffb1", "text": "limbs", "initloc": {"y": 0, "x": 0}, "size": 1}, {"color": "#e8b9b8", "text": "wounds", "initloc": {"y": 0, "x": 0}, "size": 1}, {"color": "#9cffde", "text": "flesh", "initloc": {"y": 0, "x": 0}, "size": 1}, {"color": "#e096c9", "text": "healed", "initloc": {"y": 0, "x": 0}, "size": 1}, {"color": "#5becdb", "text": "strength", "initloc": {"y": 0, "x": 0}, "size": 1}, {"color": "#c4b1f0", "text": "heal", "initloc": {"y": 0, "x": 0}, "size": 1}, {"color": "#8565b8", "text": "trapped", "initloc": {"y": 0, "x": 0}, "size": 0}, {"color": "#8bceac", "text": "causing", "initloc": {"y": 0, "x": 0}, "size": 0}, {"color": "#8cffae", "text": "bones", "initloc": {"y": 0, "x": 0}, "size": 0}, {"color": "#88edc4", "text": "spine", "initloc": {"y": 0, "x": 0}, "size": 0}, {"color": "#d59dff", "text": "human", "initloc": {"y": 0, "x": 0}, "size": 0}, {"color": "#9749ff", "text": "consciousness", "initloc": {"y": 0, "x": 0}, "size": 0}, {"color": "#afaac0", "text": "caused", "initloc": {"y": 0, "x": 0}, "size": 0}, {"color": "#78dfc6", "text": "swelling", "initloc": {"y": 0, "x": 0}, "size": 0}, {"color": "#c56afe", "text": "agony", "initloc": {"y": 0, "x": 0}, "size": 0}, {"color": "#e74ace", "text": "paralyzed", "initloc": {"y": 0, "x": 0}, "size": 0}, {"color": "#83ff92", "text": "skull", "initloc": {"y": 0, "x": 0}, "size": 0}, {"color": "#9fb6ff", "text": "healing", "initloc": {"y": 0, "x": 0}, "size": 0}, {"color": "#93e2ff", "text": "swallow", "initloc": {"y": 0, "x": 0}, "size": 0}, {"color": "#7cf6a6", "text": "body", "initloc": {"y": 0, "x": 0}, "size": 0}], "cb": 0, "zyx": [13, 51, 75], "corr_r2l": -0.06123556051484822}