{"p": 0.4376, "rgb": "#6e7d8a", "corr": 0.016625882832181856, "words": [{"color": "#9e52c9", "text": "relevant", "initloc": {"y": 0, "x": 0}, "size": 0}, {"color": "#a851b3", "text": "problem", "initloc": {"y": 0, "x": 0}, "size": 0}, {"color": "#9b57d7", "text": "suggest", "initloc": {"y": 0, "x": 0}, "size": 0}, {"color": "#9682c1", "text": "actual", "initloc": {"y": 0, "x": 0}, "size": 0}, {"color": "#a532e0", "text": "topic", "initloc": {"y": 0, "x": 0}, "size": 0}, {"color": "#bf6bd7", "text": "irrelevant", "initloc": {"y": 0, "x": 0}, "size": 0}, {"color": "#e24fef", "text": "agree", "initloc": {"y": 0, "x": 0}, "size": 0}, {"color": "#ce54cf", "text": "consider", "initloc": {"y": 0, "x": 0}, "size": 0}, {"color": "#ca37ff", "text": "understand", "initloc": {"y": 0, "x": 0}, "size": 0}, {"color": "#df4ff4", "text": "certainly", "initloc": {"y": 0, "x": 0}, "size": 0}, {"color": "#e029d4", "text": "question", "initloc": {"y": 0, "x": 0}, "size": 0}, {"color": "#c369ef", "text": "obvious", "initloc": {"y": 0, "x": 0}, "size": 0}, {"color": "#be73c9", "text": "correct", "initloc": {"y": 0, "x": 0}, "size": 0}, {"color": "#8f7774", "text": "apply", "initloc": {"y": 0, "x": 0}, "size": 0}, {"color": "#b800ba", "text": "questions", "initloc": {"y": 0, "x": 0}, "size": 0}, {"color": "#ac82dd", "text": "necessarily", "initloc": {"y": 0, "x": 0}, "size": 0}, {"color": "#5298bf", "text": "content", "initloc": {"y": 0, "x": 0}, "size": 0}, {"color": "#c250e5", "text": "arguments", "initloc": {"y": 0, "x": 0}, "size": 0}, {"color": "#cb0fbd", "text": "answer", "initloc": {"y": 0, "x": 0}, "size": 0}, {"color": "#c928f2", "text": "explain", "initloc": {"y": 0, "x": 0}, "size": 0}], "cb": 0, "zyx": [5, 40, 24], "corr_r2l": 0.12607747062126384}