{"p": 0.5888, "rgb": "#6e7f89", "corr": -0.01762958667730016, "words": [{"color": "#657f32", "text": "established", "initloc": {"y": 0, "x": 0}, "size": 0}, {"color": "#229b39", "text": "expanded", "initloc": {"y": 0, "x": 0}, "size": 0}, {"color": "#628703", "text": "district", "initloc": {"y": 0, "x": 0}, "size": 0}, {"color": "#5b9a3b", "text": "founded", "initloc": {"y": 0, "x": 0}, "size": 0}, {"color": "#34ac25", "text": "divided", "initloc": {"y": 0, "x": 0}, "size": 0}, {"color": "#556310", "text": "headquarters", "initloc": {"y": 0, "x": 0}, "size": 0}, {"color": "#947d3c", "text": "territories", "initloc": {"y": 0, "x": 0}, "size": 0}, {"color": "#8e6218", "text": "council", "initloc": {"y": 0, "x": 0}, "size": 0}, {"color": "#719f13", "text": "united", "initloc": {"y": 0, "x": 0}, "size": 0}, {"color": "#99a539", "text": "belonging", "initloc": {"y": 0, "x": 0}, "size": 0}, {"color": "#589c26", "text": "association", "initloc": {"y": 0, "x": 0}, "size": 0}, {"color": "#1fc915", "text": "largest", "initloc": {"y": 0, "x": 0}, "size": 0}, {"color": "#7a6d3b", "text": "principal", "initloc": {"y": 0, "x": 0}, "size": 0}, {"color": "#616e47", "text": "institute", "initloc": {"y": 0, "x": 0}, "size": 0}, {"color": "#379326", "text": "divisions", "initloc": {"y": 0, "x": 0}, "size": 0}, {"color": "#4ab626", "text": "formerly", "initloc": {"y": 0, "x": 0}, "size": 0}, {"color": "#4f8e25", "text": "villages", "initloc": {"y": 0, "x": 0}, "size": 0}, {"color": "#4c7821", "text": "newly", "initloc": {"y": 0, "x": 0}, "size": 0}, {"color": "#398d15", "text": "city's", "initloc": {"y": 0, "x": 0}, "size": 0}, {"color": "#828130", "text": "settlement", "initloc": {"y": 0, "x": 0}, "size": 0}], "cb": 0, "zyx": [5, 42, 60], "corr_r2l": -0.056074863175626634}