{"p": 0.3386, "rgb": "#6f828f", "corr": 0.04042965010403017, "words": [{"color": "#94c7ee", "text": "qualities", "initloc": {"y": 0, "x": 0}, "size": 0}, {"color": "#cd80c0", "text": "virtue", "initloc": {"y": 0, "x": 0}, "size": 0}, {"color": "#cb59dd", "text": "regard", "initloc": {"y": 0, "x": 0}, "size": 0}, {"color": "#6073e8", "text": "aspects", "initloc": {"y": 0, "x": 0}, "size": 0}, {"color": "#9fa7ba", "text": "universally", "initloc": {"y": 0, "x": 0}, "size": 0}, {"color": "#9555e4", "text": "notions", "initloc": {"y": 0, "x": 0}, "size": 0}, {"color": "#a754de", "text": "intellectual", "initloc": {"y": 0, "x": 0}, "size": 0}, {"color": "#a697a3", "text": "solely", "initloc": {"y": 0, "x": 0}, "size": 0}, {"color": "#9c8be4", "text": "purely", "initloc": {"y": 0, "x": 0}, "size": 0}, {"color": "#ea5fff", "text": "belief", "initloc": {"y": 0, "x": 0}, "size": 0}, {"color": "#db49e9", "text": "motives", "initloc": {"y": 0, "x": 0}, "size": 0}, {"color": "#b861f9", "text": "beings", "initloc": {"y": 0, "x": 0}, "size": 0}, {"color": "#af62f3", "text": "notion", "initloc": {"y": 0, "x": 0}, "size": 0}, {"color": "#d073fe", "text": "contrary", "initloc": {"y": 0, "x": 0}, "size": 0}, {"color": "#ac82dd", "text": "necessarily", "initloc": {"y": 0, "x": 0}, "size": 0}, {"color": "#df4edc", "text": "desires", "initloc": {"y": 0, "x": 0}, "size": 0}, {"color": "#a38cdb", "text": "influence", "initloc": {"y": 0, "x": 0}, "size": 0}, {"color": "#a17bd3", "text": "myths", "initloc": {"y": 0, "x": 0}, "size": 0}, {"color": "#8772d8", "text": "fundamental", "initloc": {"y": 0, "x": 0}, "size": 0}, {"color": "#cb4efe", "text": "psychological", "initloc": {"y": 0, "x": 0}, "size": 0}], "cb": 0, "zyx": [23, 64, 37], "corr_r2l": 0.03848060110931379}