{"p": 0.0077, "rgb": "#ff4f5a", "corr": 0.2655607326017097, "words": [{"color": "#ff4677", "text": "killed", "initloc": {"y": 0, "x": 0}, "size": 18}, {"color": "#ff488f", "text": "murder", "initloc": {"y": 0, "x": 0}, "size": 16}, {"color": "#ff2d65", "text": "arrest", "initloc": {"y": 0, "x": 0}, "size": 15}, {"color": "#ff287d", "text": "murdered", "initloc": {"y": 0, "x": 0}, "size": 15}, {"color": "#ff2b7c", "text": "pregnant", "initloc": {"y": 0, "x": 0}, "size": 14}, {"color": "#ff719c", "text": "victim", "initloc": {"y": 0, "x": 0}, "size": 14}, {"color": "#ff023e", "text": "wife", "initloc": {"y": 0, "x": 0}, "size": 13}, {"color": "#ff5ed6", "text": "innocent", "initloc": {"y": 0, "x": 0}, "size": 13}, {"color": "#ff30af", "text": "murderer", "initloc": {"y": 0, "x": 0}, "size": 12}, {"color": "#ff1bb7", "text": "suicide", "initloc": {"y": 0, "x": 0}, "size": 12}, {"color": "#ff235e", "text": "died", "initloc": {"y": 0, "x": 0}, "size": 12}, {"color": "#ff1e3c", "text": "arrested", "initloc": {"y": 0, "x": 0}, "size": 12}, {"color": "#ff5152", "text": "hanged", "initloc": {"y": 0, "x": 0}, "size": 11}, {"color": "#ff82cc", "text": "kill", "initloc": {"y": 0, "x": 0}, "size": 11}, {"color": "#ff4aab", "text": "threatening", "initloc": {"y": 0, "x": 0}, "size": 11}, {"color": "#ff5ce1", "text": "danger", "initloc": {"y": 0, "x": 0}, "size": 11}, {"color": "#fc79be", "text": "poisoned", "initloc": {"y": 0, "x": 0}, "size": 11}, {"color": "#ff2c9d", "text": "apparently", "initloc": {"y": 0, "x": 0}, "size": 11}, {"color": "#ff3057", "text": "jail", "initloc": {"y": 0, "x": 0}, "size": 11}, {"color": "#f362b4", "text": "dead", "initloc": {"y": 0, "x": 0}, "size": 11}], "cb": 2, "zyx": [24, 30, 49], "corr_r2l": 0.25456577521272367}