{"p": 0.2004, "rgb": "#6e7f89", "corr": 0.06944436761527076, "words": [{"color": "#5298bf", "text": "content", "initloc": {"y": 0, "x": 0}, "size": 0}, {"color": "#428bc9", "text": "useful", "initloc": {"y": 0, "x": 0}, "size": 0}, {"color": "#996be4", "text": "exist", "initloc": {"y": 0, "x": 0}, "size": 0}, {"color": "#ac82dd", "text": "necessarily", "initloc": {"y": 0, "x": 0}, "size": 0}, {"color": "#6a8c9f", "text": "specific", "initloc": {"y": 0, "x": 0}, "size": 0}, {"color": "#9894cd", "text": "definition", "initloc": {"y": 0, "x": 0}, "size": 0}, {"color": "#5e9057", "text": "value", "initloc": {"y": 0, "x": 0}, "size": 0}, {"color": "#7278c7", "text": "rely", "initloc": {"y": 0, "x": 0}, "size": 0}, {"color": "#3fdc6a", "text": "product", "initloc": {"y": 0, "x": 0}, "size": 0}, {"color": "#607db1", "text": "depend", "initloc": {"y": 0, "x": 0}, "size": 0}, {"color": "#9a7893", "text": "benefit", "initloc": {"y": 0, "x": 0}, "size": 0}, {"color": "#478ec5", "text": "complexity", "initloc": {"y": 0, "x": 0}, "size": 0}, {"color": "#bf6bd7", "text": "irrelevant", "initloc": {"y": 0, "x": 0}, "size": 0}, {"color": "#3eb87e", "text": "requires", "initloc": {"y": 0, "x": 0}, "size": 0}, {"color": "#609998", "text": "solution", "initloc": {"y": 0, "x": 0}, "size": 0}, {"color": "#9c8be4", "text": "purely", "initloc": {"y": 0, "x": 0}, "size": 0}, {"color": "#7b72ad", "text": "necessary", "initloc": {"y": 0, "x": 0}, "size": 0}, {"color": "#459bc4", "text": "source", "initloc": {"y": 0, "x": 0}, "size": 0}, {"color": "#14cca7", "text": "create", "initloc": {"y": 0, "x": 0}, "size": 0}, {"color": "#a159f3", "text": "meaningless", "initloc": {"y": 0, "x": 0}, "size": 0}], "cb": 0, "zyx": [5, 45, 23], "corr_r2l": 0.17482261061407708}