{"p": 0.0626, "rgb": "#6b848b", "corr": 0.16324337350169765, "words": [{"color": "#5ef985", "text": "derived", "initloc": {"y": 0, "x": 0}, "size": 0}, {"color": "#2ae18a", "text": "forms", "initloc": {"y": 0, "x": 0}, "size": 0}, {"color": "#4df29a", "text": "characteristics", "initloc": {"y": 0, "x": 0}, "size": 0}, {"color": "#3effbd", "text": "characteristic", "initloc": {"y": 0, "x": 0}, "size": 0}, {"color": "#63e08d", "text": "widely", "initloc": {"y": 0, "x": 0}, "size": 0}, {"color": "#1bc5ab", "text": "elements", "initloc": {"y": 0, "x": 0}, "size": 0}, {"color": "#0efb81", "text": "varying", "initloc": {"y": 0, "x": 0}, "size": 0}, {"color": "#5eb48e", "text": "largely", "initloc": {"y": 0, "x": 0}, "size": 0}, {"color": "#52c8c0", "text": "highly", "initloc": {"y": 0, "x": 0}, "size": 0}, {"color": "#25d98c", "text": "varied", "initloc": {"y": 0, "x": 0}, "size": 0}, {"color": "#43dc9d", "text": "distinct", "initloc": {"y": 0, "x": 0}, "size": 0}, {"color": "#53e6e1", "text": "natural", "initloc": {"y": 0, "x": 0}, "size": 0}, {"color": "#53a38c", "text": "significant", "initloc": {"y": 0, "x": 0}, "size": 0}, {"color": "#1cf590", "text": "contrast", "initloc": {"y": 0, "x": 0}, "size": 0}, {"color": "#41fe86", "text": "contain", "initloc": {"y": 0, "x": 0}, "size": 0}, {"color": "#1ad45c", "text": "regions", "initloc": {"y": 0, "x": 0}, "size": 0}, {"color": "#44f87e", "text": "whereas", "initloc": {"y": 0, "x": 0}, "size": 0}, {"color": "#09ff89", "text": "produces", "initloc": {"y": 0, "x": 0}, "size": 0}, {"color": "#09d99e", "text": "unique", "initloc": {"y": 0, "x": 0}, "size": 0}, {"color": "#47ff7f", "text": "unlike", "initloc": {"y": 0, "x": 0}, "size": 0}], "cb": 1, "zyx": [11, 19, 26], "corr_r2l": -0.019953555571835126}