{"p": 0.8437, "rgb": "#6290b3", "corr": -0.06176695964859552, "words": [{"color": "#68eb6a", "text": "bread", "initloc": {"y": 0, "x": 0}, "size": 2}, {"color": "#69ac64", "text": "sandwich", "initloc": {"y": 0, "x": 0}, "size": 2}, {"color": "#74ecca", "text": "sour", "initloc": {"y": 0, "x": 0}, "size": 1}, {"color": "#5bf589", "text": "butter", "initloc": {"y": 0, "x": 0}, "size": 1}, {"color": "#65ff95", "text": "chopped", "initloc": {"y": 0, "x": 0}, "size": 1}, {"color": "#d26991", "text": "alcoholic", "initloc": {"y": 0, "x": 0}, "size": 1}, {"color": "#1dce8e", "text": "filling", "initloc": {"y": 0, "x": 0}, "size": 1}, {"color": "#5cef77", "text": "cheese", "initloc": {"y": 0, "x": 0}, "size": 1}, {"color": "#31f7d5", "text": "mixing", "initloc": {"y": 0, "x": 0}, "size": 1}, {"color": "#1dffb2", "text": "crust", "initloc": {"y": 0, "x": 0}, "size": 1}, {"color": "#a8a75d", "text": "patty", "initloc": {"y": 0, "x": 0}, "size": 1}, {"color": "#44da6f", "text": "oven", "initloc": {"y": 0, "x": 0}, "size": 1}, {"color": "#32e0ab", "text": "chalk", "initloc": {"y": 0, "x": 0}, "size": 1}, {"color": "#4da6a8", "text": "baked", "initloc": {"y": 0, "x": 0}, "size": 1}, {"color": "#49ec67", "text": "dish", "initloc": {"y": 0, "x": 0}, "size": 1}, {"color": "#6e9c67", "text": "sandwiches", "initloc": {"y": 0, "x": 0}, "size": 1}, {"color": "#4eff88", "text": "lemon", "initloc": {"y": 0, "x": 0}, "size": 1}, {"color": "#bc8365", "text": "poverty", "initloc": {"y": 0, "x": 0}, "size": 1}, {"color": "#63fd8d", "text": "vegetable", "initloc": {"y": 0, "x": 0}, "size": 1}, {"color": "#b43edb", "text": "secrets", "initloc": {"y": 0, "x": 0}, "size": 1}], "cb": 0, "zyx": [14, 39, 62], "corr_r2l": -0.055700640310578885}