{"p": 0.1071, "rgb": "#48ca8a", "corr": 0.09459064150271941, "words": [{"color": "#18ff60", "text": "orange", "initloc": {"y": 0, "x": 0}, "size": 3}, {"color": "#3eff4c", "text": "brown", "initloc": {"y": 0, "x": 0}, "size": 3}, {"color": "#43ff78", "text": "pink", "initloc": {"y": 0, "x": 0}, "size": 3}, {"color": "#39f97b", "text": "cream", "initloc": {"y": 0, "x": 0}, "size": 2}, {"color": "#7ff69e", "text": "ginger", "initloc": {"y": 0, "x": 0}, "size": 2}, {"color": "#57e084", "text": "chocolate", "initloc": {"y": 0, "x": 0}, "size": 2}, {"color": "#77ce5a", "text": "brandy", "initloc": {"y": 0, "x": 0}, "size": 2}, {"color": "#6b6400", "text": "bought", "initloc": {"y": 0, "x": 0}, "size": 2}, {"color": "#29f824", "text": "brand", "initloc": {"y": 0, "x": 0}, "size": 2}, {"color": "#4eff88", "text": "lemon", "initloc": {"y": 0, "x": 0}, "size": 2}, {"color": "#1bff80", "text": "purple", "initloc": {"y": 0, "x": 0}, "size": 2}, {"color": "#66d364", "text": "candy", "initloc": {"y": 0, "x": 0}, "size": 2}, {"color": "#44f794", "text": "juice", "initloc": {"y": 0, "x": 0}, "size": 2}, {"color": "#74ecca", "text": "sour", "initloc": {"y": 0, "x": 0}, "size": 2}, {"color": "#0bff4d", "text": "blue", "initloc": {"y": 0, "x": 0}, "size": 2}, {"color": "#45fd7a", "text": "cherry", "initloc": {"y": 0, "x": 0}, "size": 2}, {"color": "#1cff20", "text": "silver", "initloc": {"y": 0, "x": 0}, "size": 2}, {"color": "#5bd48f", "text": "pudding", "initloc": {"y": 0, "x": 0}, "size": 2}, {"color": "#6ddd24", "text": "outfit", "initloc": {"y": 0, "x": 0}, "size": 2}, {"color": "#60c700", "text": "sold", "initloc": {"y": 0, "x": 0}, "size": 2}], "cb": 0, "zyx": [17, 85, 61], "corr_r2l": 0.05288393588789232}