{"p": 0.5639, "rgb": "#d6c54c", "corr": -0.013817408791194394, "words": [{"color": "#c59874", "text": "raising", "initloc": {"y": 0, "x": 0}, "size": 3}, {"color": "#92b436", "text": "arquette", "initloc": {"y": 0, "x": 0}, "size": 3}, {"color": "#78c129", "text": "lothario", "initloc": {"y": 0, "x": 0}, "size": 2}, {"color": "#7ca52b", "text": "chloe's", "initloc": {"y": 0, "x": 0}, "size": 2}, {"color": "#7bf58d", "text": "potato", "initloc": {"y": 0, "x": 0}, "size": 2}, {"color": "#d9844a", "text": "raise", "initloc": {"y": 0, "x": 0}, "size": 2}, {"color": "#ce7606", "text": "worker", "initloc": {"y": 0, "x": 0}, "size": 2}, {"color": "#81bc19", "text": "mattingly", "initloc": {"y": 0, "x": 0}, "size": 2}, {"color": "#82b418", "text": "selling", "initloc": {"y": 0, "x": 0}, "size": 2}, {"color": "#48d12f", "text": "khu", "initloc": {"y": 0, "x": 0}, "size": 2}, {"color": "#4ecc26", "text": "tartabull", "initloc": {"y": 0, "x": 0}, "size": 2}, {"color": "#3fd628", "text": "klv", "initloc": {"y": 0, "x": 0}, "size": 2}, {"color": "#47cf2e", "text": "showalter's", "initloc": {"y": 0, "x": 0}, "size": 2}, {"color": "#45cc2f", "text": "klp", "initloc": {"y": 0, "x": 0}, "size": 2}, {"color": "#789244", "text": "food", "initloc": {"y": 0, "x": 0}, "size": 2}, {"color": "#e16d5b", "text": "welfare", "initloc": {"y": 0, "x": 0}, "size": 2}, {"color": "#68eb6a", "text": "bread", "initloc": {"y": 0, "x": 0}, "size": 2}, {"color": "#c2891e", "text": "household", "initloc": {"y": 0, "x": 0}, "size": 2}, {"color": "#50d42e", "text": "mcgough", "initloc": {"y": 0, "x": 0}, "size": 2}, {"color": "#40cf2d", "text": "kdg", "initloc": {"y": 0, "x": 0}, "size": 2}], "cb": 0, "zyx": [11, 38, 48], "corr_l2r": -0.006945317968542208}