{"p": 0.0245, "rgb": "#00b37c", "corr": 0.19639001673569517, "words": [{"color": "#11c404", "text": "approximately", "initloc": {"y": 0, "x": 0}, "size": 6}, {"color": "#04b644", "text": "areas", "initloc": {"y": 0, "x": 0}, "size": 6}, {"color": "#5acb4a", "text": "reduced", "initloc": {"y": 0, "x": 0}, "size": 5}, {"color": "#0ed729", "text": "roughly", "initloc": {"y": 0, "x": 0}, "size": 5}, {"color": "#3eff5b", "text": "excess", "initloc": {"y": 0, "x": 0}, "size": 5}, {"color": "#0eee62", "text": "combined", "initloc": {"y": 0, "x": 0}, "size": 5}, {"color": "#00fe1e", "text": "smaller", "initloc": {"y": 0, "x": 0}, "size": 5}, {"color": "#3fc4d0", "text": "absorbed", "initloc": {"y": 0, "x": 0}, "size": 5}, {"color": "#00ff50", "text": "diameter", "initloc": {"y": 0, "x": 0}, "size": 5}, {"color": "#2ae18a", "text": "forms", "initloc": {"y": 0, "x": 0}, "size": 5}, {"color": "#0fff36", "text": "larger", "initloc": {"y": 0, "x": 0}, "size": 5}, {"color": "#4ef86a", "text": "resulting", "initloc": {"y": 0, "x": 0}, "size": 5}, {"color": "#18b874", "text": "surrounding", "initloc": {"y": 0, "x": 0}, "size": 5}, {"color": "#09ff89", "text": "produces", "initloc": {"y": 0, "x": 0}, "size": 5}, {"color": "#16f286", "text": "parts", "initloc": {"y": 0, "x": 0}, "size": 5}, {"color": "#00ff8a", "text": "surfaces", "initloc": {"y": 0, "x": 0}, "size": 5}, {"color": "#03ffbb", "text": "dense", "initloc": {"y": 0, "x": 0}, "size": 5}, {"color": "#4ad458", "text": "vessels", "initloc": {"y": 0, "x": 0}, "size": 5}, {"color": "#20da59", "text": "portion", "initloc": {"y": 0, "x": 0}, "size": 4}, {"color": "#00ff46", "text": "mm", "initloc": {"y": 0, "x": 0}, "size": 4}], "cb": 1, "zyx": [17, 22, 70], "corr_l2r": 0.2515405370110875}