{"p": 0.0349, "rgb": "#5967af", "corr": 0.16519387348504955, "words": [{"color": "#678073", "text": "success", "initloc": {"y": 0, "x": 0}, "size": 2}, {"color": "#8d7230", "text": "career", "initloc": {"y": 0, "x": 0}, "size": 2}, {"color": "#157088", "text": "pace", "initloc": {"y": 0, "x": 0}, "size": 2}, {"color": "#6e9612", "text": "winning", "initloc": {"y": 0, "x": 0}, "size": 2}, {"color": "#3e8dd0", "text": "excellent", "initloc": {"y": 0, "x": 0}, "size": 2}, {"color": "#2c9f61", "text": "performance", "initloc": {"y": 0, "x": 0}, "size": 2}, {"color": "#492acc", "text": "exciting", "initloc": {"y": 0, "x": 0}, "size": 1}, {"color": "#7f8f50", "text": "successful", "initloc": {"y": 0, "x": 0}, "size": 1}, {"color": "#835d6f", "text": "practice", "initloc": {"y": 0, "x": 0}, "size": 1}, {"color": "#7e51c1", "text": "enthusiasm", "initloc": {"y": 0, "x": 0}, "size": 1}, {"color": "#81425a", "text": "instructor", "initloc": {"y": 0, "x": 0}, "size": 1}, {"color": "#9d45bc", "text": "impressed", "initloc": {"y": 0, "x": 0}, "size": 1}, {"color": "#6516c7", "text": "learning", "initloc": {"y": 0, "x": 0}, "size": 1}, {"color": "#9082a8", "text": "talented", "initloc": {"y": 0, "x": 0}, "size": 1}, {"color": "#88c532", "text": "athlete", "initloc": {"y": 0, "x": 0}, "size": 1}, {"color": "#448000", "text": "team", "initloc": {"y": 0, "x": 0}, "size": 1}, {"color": "#25b290", "text": "superb", "initloc": {"y": 0, "x": 0}, "size": 1}, {"color": "#447c5f", "text": "goal", "initloc": {"y": 0, "x": 0}, "size": 1}, {"color": "#569fa3", "text": "skill", "initloc": {"y": 0, "x": 0}, "size": 1}, {"color": "#665792", "text": "challenge", "initloc": {"y": 0, "x": 0}, "size": 1}], "cb": 1, "zyx": [7, 39, 23], "corr_l2r": -0.035461456017791874}