{"p": 0.8346, "rgb": "#61799e", "corr": -0.07465593140104103, "words": [{"color": "#288b5a", "text": "throughout", "initloc": {"y": 0, "x": 0}, "size": 0}, {"color": "#3d7514", "text": "city", "initloc": {"y": 0, "x": 0}, "size": 0}, {"color": "#5d28cb", "text": "distant", "initloc": {"y": 0, "x": 0}, "size": 0}, {"color": "#947aa3", "text": "grew", "initloc": {"y": 0, "x": 0}, "size": 0}, {"color": "#5e7a1c", "text": "village", "initloc": {"y": 0, "x": 0}, "size": 0}, {"color": "#4ea94a", "text": "numerous", "initloc": {"y": 0, "x": 0}, "size": 0}, {"color": "#29a54a", "text": "southern", "initloc": {"y": 0, "x": 0}, "size": 0}, {"color": "#4a8404", "text": "several", "initloc": {"y": 0, "x": 0}, "size": 0}, {"color": "#88622f", "text": "remained", "initloc": {"y": 0, "x": 0}, "size": 0}, {"color": "#18b874", "text": "surrounding", "initloc": {"y": 0, "x": 0}, "size": 0}, {"color": "#10a35b", "text": "scattered", "initloc": {"y": 0, "x": 0}, "size": 0}, {"color": "#5b6412", "text": "during", "initloc": {"y": 0, "x": 0}, "size": 0}, {"color": "#8f915b", "text": "accompanied", "initloc": {"y": 0, "x": 0}, "size": 0}, {"color": "#446f3e", "text": "began", "initloc": {"y": 0, "x": 0}, "size": 0}, {"color": "#8c7e3c", "text": "became", "initloc": {"y": 0, "x": 0}, "size": 0}, {"color": "#46c005", "text": "including", "initloc": {"y": 0, "x": 0}, "size": 0}, {"color": "#565005", "text": "town", "initloc": {"y": 0, "x": 0}, "size": 0}, {"color": "#e00041", "text": "lived", "initloc": {"y": 0, "x": 0}, "size": 0}, {"color": "#5f7e62", "text": "inhabited", "initloc": {"y": 0, "x": 0}, "size": 0}, {"color": "#57615e", "text": "countryside", "initloc": {"y": 0, "x": 0}, "size": 0}], "cb": 0, "zyx": [22, 63, 53], "corr_l2r": -0.07708116991291074}