{"p": 0.6383, "rgb": "#687f9a", "corr": -0.025993400490182308, "words": [{"color": "#e53ab4", "text": "anyone", "initloc": {"y": 0, "x": 0}, "size": 0}, {"color": "#c044e6", "text": "honestly", "initloc": {"y": 0, "x": 0}, "size": 0}, {"color": "#b843ba", "text": "else", "initloc": {"y": 0, "x": 0}, "size": 0}, {"color": "#de3fcc", "text": "anybody", "initloc": {"y": 0, "x": 0}, "size": 0}, {"color": "#d333bf", "text": "know", "initloc": {"y": 0, "x": 0}, "size": 0}, {"color": "#b926a9", "text": "everyone", "initloc": {"y": 0, "x": 0}, "size": 0}, {"color": "#d559d6", "text": "seriously", "initloc": {"y": 0, "x": 0}, "size": 0}, {"color": "#c428b1", "text": "anyway", "initloc": {"y": 0, "x": 0}, "size": 0}, {"color": "#c454d2", "text": "think", "initloc": {"y": 0, "x": 0}, "size": 0}, {"color": "#f243e2", "text": "saying", "initloc": {"y": 0, "x": 0}, "size": 0}, {"color": "#9754d7", "text": "wow", "initloc": {"y": 0, "x": 0}, "size": 0}, {"color": "#b54af8", "text": "seem", "initloc": {"y": 0, "x": 0}, "size": 0}, {"color": "#b744cc", "text": "exactly", "initloc": {"y": 0, "x": 0}, "size": 0}, {"color": "#d742b1", "text": "somebody", "initloc": {"y": 0, "x": 0}, "size": 0}, {"color": "#aa5be0", "text": "definitely", "initloc": {"y": 0, "x": 0}, "size": 0}, {"color": "#e76cdb", "text": "stupid", "initloc": {"y": 0, "x": 0}, "size": 0}, {"color": "#ba4fbd", "text": "guess", "initloc": {"y": 0, "x": 0}, "size": 0}, {"color": "#ca37ff", "text": "understand", "initloc": {"y": 0, "x": 0}, "size": 0}, {"color": "#aa28f3", "text": "thinking", "initloc": {"y": 0, "x": 0}, "size": 0}, {"color": "#d344ce", "text": "okay", "initloc": {"y": 0, "x": 0}, "size": 0}], "cb": 0, "zyx": [18, 76, 29], "corr_l2r": -0.08697608807156879}