{"p": 0.0994, "rgb": "#6a7f9d", "corr": 0.14300371226945358, "words": [{"color": "#e24fef", "text": "agree", "initloc": {"y": 0, "x": 0}, "size": 0}, {"color": "#c044e6", "text": "honestly", "initloc": {"y": 0, "x": 0}, "size": 0}, {"color": "#ca37ff", "text": "understand", "initloc": {"y": 0, "x": 0}, "size": 0}, {"color": "#e559b8", "text": "shouldn't", "initloc": {"y": 0, "x": 0}, "size": 0}, {"color": "#b879bc", "text": "aren't", "initloc": {"y": 0, "x": 0}, "size": 0}, {"color": "#df4ff4", "text": "certainly", "initloc": {"y": 0, "x": 0}, "size": 0}, {"color": "#c951e0", "text": "personally", "initloc": {"y": 0, "x": 0}, "size": 0}, {"color": "#ce54cf", "text": "consider", "initloc": {"y": 0, "x": 0}, "size": 0}, {"color": "#c54fec", "text": "frankly", "initloc": {"y": 0, "x": 0}, "size": 0}, {"color": "#b944e2", "text": "absolutely", "initloc": {"y": 0, "x": 0}, "size": 0}, {"color": "#e241df", "text": "honest", "initloc": {"y": 0, "x": 0}, "size": 0}, {"color": "#ea63c2", "text": "obviously", "initloc": {"y": 0, "x": 0}, "size": 0}, {"color": "#cb79c3", "text": "ridiculous", "initloc": {"y": 0, "x": 0}, "size": 0}, {"color": "#cc73c7", "text": "regardless", "initloc": {"y": 0, "x": 0}, "size": 0}, {"color": "#e45bb0", "text": "assume", "initloc": {"y": 0, "x": 0}, "size": 0}, {"color": "#ac82dd", "text": "necessarily", "initloc": {"y": 0, "x": 0}, "size": 0}, {"color": "#da3cff", "text": "admit", "initloc": {"y": 0, "x": 0}, "size": 0}, {"color": "#db69d8", "text": "cares", "initloc": {"y": 0, "x": 0}, "size": 0}, {"color": "#c578d7", "text": "isn't", "initloc": {"y": 0, "x": 0}, "size": 0}, {"color": "#b54af8", "text": "seem", "initloc": {"y": 0, "x": 0}, "size": 0}], "cb": 1, "zyx": [19, 71, 28], "corr_l2r": 0.2520513457835914}