{"p": 0.1862, "rgb": "#687f9a", "corr": 0.0669918023215164, "words": [{"color": "#229b39", "text": "expanded", "initloc": {"y": 0, "x": 0}, "size": 0}, {"color": "#379304", "text": "division", "initloc": {"y": 0, "x": 0}, "size": 0}, {"color": "#278f18", "text": "operated", "initloc": {"y": 0, "x": 0}, "size": 0}, {"color": "#556310", "text": "headquarters", "initloc": {"y": 0, "x": 0}, "size": 0}, {"color": "#379326", "text": "divisions", "initloc": {"y": 0, "x": 0}, "size": 0}, {"color": "#4c7821", "text": "newly", "initloc": {"y": 0, "x": 0}, "size": 0}, {"color": "#2a5d0d", "text": "completed", "initloc": {"y": 0, "x": 0}, "size": 0}, {"color": "#549d00", "text": "selected", "initloc": {"y": 0, "x": 0}, "size": 0}, {"color": "#398d15", "text": "city's", "initloc": {"y": 0, "x": 0}, "size": 0}, {"color": "#468515", "text": "international", "initloc": {"y": 0, "x": 0}, "size": 0}, {"color": "#1da400", "text": "annual", "initloc": {"y": 0, "x": 0}, "size": 0}, {"color": "#589c26", "text": "association", "initloc": {"y": 0, "x": 0}, "size": 0}, {"color": "#205c21", "text": "facility", "initloc": {"y": 0, "x": 0}, "size": 0}, {"color": "#46b311", "text": "estimated", "initloc": {"y": 0, "x": 0}, "size": 0}, {"color": "#34ac25", "text": "divided", "initloc": {"y": 0, "x": 0}, "size": 0}, {"color": "#58853e", "text": "georgia", "initloc": {"y": 0, "x": 0}, "size": 0}, {"color": "#717136", "text": "massachusetts", "initloc": {"y": 0, "x": 0}, "size": 0}, {"color": "#1fc915", "text": "largest", "initloc": {"y": 0, "x": 0}, "size": 0}, {"color": "#11c404", "text": "approximately", "initloc": {"y": 0, "x": 0}, "size": 0}, {"color": "#3db344", "text": "delta", "initloc": {"y": 0, "x": 0}, "size": 0}], "cb": 0, "zyx": [11, 78, 44], "corr_l2r": -0.017243894043559534}