{"p": 0.5894, "rgb": "#ed3a1d", "corr": -0.007821464661639008, "words": [{"color": "#f9396a", "text": "accident", "initloc": {"y": 0, "x": 0}, "size": 7}, {"color": "#ff7476", "text": "infant", "initloc": {"y": 0, "x": 0}, "size": 7}, {"color": "#bf2660", "text": "ambulance", "initloc": {"y": 0, "x": 0}, "size": 6}, {"color": "#ff1645", "text": "custody", "initloc": {"y": 0, "x": 0}, "size": 6}, {"color": "#ae1f34", "text": "nursing", "initloc": {"y": 0, "x": 0}, "size": 5}, {"color": "#be476d", "text": "foster", "initloc": {"y": 0, "x": 0}, "size": 5}, {"color": "#a7000c", "text": "attend", "initloc": {"y": 0, "x": 0}, "size": 5}, {"color": "#9f1b29", "text": "admission", "initloc": {"y": 0, "x": 0}, "size": 5}, {"color": "#d72b60", "text": "courtroom", "initloc": {"y": 0, "x": 0}, "size": 5}, {"color": "#eb467e", "text": "parent", "initloc": {"y": 0, "x": 0}, "size": 5}, {"color": "#ff5757", "text": "mothers", "initloc": {"y": 0, "x": 0}, "size": 5}, {"color": "#ff2b7c", "text": "pregnant", "initloc": {"y": 0, "x": 0}, "size": 4}, {"color": "#9f13cd", "text": "unexpected", "initloc": {"y": 0, "x": 0}, "size": 4}, {"color": "#f758f5", "text": "reacted", "initloc": {"y": 0, "x": 0}, "size": 4}, {"color": "#8a5908", "text": "driver's", "initloc": {"y": 0, "x": 0}, "size": 4}, {"color": "#ff3732", "text": "attorney", "initloc": {"y": 0, "x": 0}, "size": 4}, {"color": "#ff287d", "text": "murdered", "initloc": {"y": 0, "x": 0}, "size": 4}, {"color": "#7e7805", "text": "seat", "initloc": {"y": 0, "x": 0}, "size": 4}, {"color": "#b6802c", "text": "aged", "initloc": {"y": 0, "x": 0}, "size": 4}, {"color": "#c90940", "text": "friend's", "initloc": {"y": 0, "x": 0}, "size": 4}], "cb": 0, "zyx": [11, 60, 25], "corr_l2r": -0.07912291027029253}