{"p": 0.2869, "rgb": "#697f99", "corr": 0.018205842144677613, "words": [{"color": "#8d6812", "text": "earn", "initloc": {"y": 0, "x": 0}, "size": 0}, {"color": "#94511c", "text": "hired", "initloc": {"y": 0, "x": 0}, "size": 0}, {"color": "#843700", "text": "manager", "initloc": {"y": 0, "x": 0}, "size": 0}, {"color": "#ae6799", "text": "mitch", "initloc": {"y": 0, "x": 0}, "size": 0}, {"color": "#a49c66", "text": "pat", "initloc": {"y": 0, "x": 0}, "size": 0}, {"color": "#b9495e", "text": "ryan", "initloc": {"y": 0, "x": 0}, "size": 0}, {"color": "#6c1610", "text": "college", "initloc": {"y": 0, "x": 0}, "size": 0}, {"color": "#c78273", "text": "sean", "initloc": {"y": 0, "x": 0}, "size": 0}, {"color": "#b68559", "text": "rob", "initloc": {"y": 0, "x": 0}, "size": 0}, {"color": "#ff285c", "text": "lawyer", "initloc": {"y": 0, "x": 0}, "size": 0}, {"color": "#93ae00", "text": "yankees", "initloc": {"y": 0, "x": 0}, "size": 0}, {"color": "#c73092", "text": "fellow", "initloc": {"y": 0, "x": 0}, "size": 0}, {"color": "#af3531", "text": "retire", "initloc": {"y": 0, "x": 0}, "size": 0}, {"color": "#772f37", "text": "graduate", "initloc": {"y": 0, "x": 0}, "size": 0}, {"color": "#c2535c", "text": "rep", "initloc": {"y": 0, "x": 0}, "size": 0}, {"color": "#a79945", "text": "joe", "initloc": {"y": 0, "x": 0}, "size": 0}, {"color": "#a35d36", "text": "charity", "initloc": {"y": 0, "x": 0}, "size": 0}, {"color": "#c32082", "text": "interview", "initloc": {"y": 0, "x": 0}, "size": 0}, {"color": "#7b9503", "text": "earned", "initloc": {"y": 0, "x": 0}, "size": 0}, {"color": "#6b2500", "text": "tickets", "initloc": {"y": 0, "x": 0}, "size": 0}], "cb": 0, "zyx": [3, 51, 38], "corr_l2r": -0.05385284773576219}