{"p": 0.6502, "rgb": "#67809a", "corr": -0.0336403841300722, "words": [{"color": "#56844e", "text": "into", "initloc": {"y": 0, "x": 0}, "size": 0}, {"color": "#87a143", "text": "or", "initloc": {"y": 0, "x": 0}, "size": 0}, {"color": "#6b828c", "text": "can", "initloc": {"y": 0, "x": 0}, "size": 0}, {"color": "#7cf6a6", "text": "body", "initloc": {"y": 0, "x": 0}, "size": 0}, {"color": "#807189", "text": "it", "initloc": {"y": 0, "x": 0}, "size": 0}, {"color": "#8d4b50", "text": "to", "initloc": {"y": 0, "x": 0}, "size": 0}, {"color": "#87c578", "text": "hand", "initloc": {"y": 0, "x": 0}, "size": 0}, {"color": "#8e545a", "text": "then", "initloc": {"y": 0, "x": 0}, "size": 0}, {"color": "#799043", "text": "with", "initloc": {"y": 0, "x": 0}, "size": 0}, {"color": "#7f8832", "text": "a", "initloc": {"y": 0, "x": 0}, "size": 0}, {"color": "#8c9876", "text": "is", "initloc": {"y": 0, "x": 0}, "size": 0}, {"color": "#7a9765", "text": "are", "initloc": {"y": 0, "x": 0}, "size": 0}, {"color": "#59ff6b", "text": "legs", "initloc": {"y": 0, "x": 0}, "size": 0}, {"color": "#557b63", "text": "down", "initloc": {"y": 0, "x": 0}, "size": 0}, {"color": "#6e7943", "text": "and", "initloc": {"y": 0, "x": 0}, "size": 0}, {"color": "#71ffb6", "text": "skin", "initloc": {"y": 0, "x": 0}, "size": 0}, {"color": "#2babd7", "text": "slowly", "initloc": {"y": 0, "x": 0}, "size": 0}, {"color": "#579fb4", "text": "sometimes", "initloc": {"y": 0, "x": 0}, "size": 0}, {"color": "#85c97c", "text": "head", "initloc": {"y": 0, "x": 0}, "size": 0}, {"color": "#708032", "text": "the", "initloc": {"y": 0, "x": 0}, "size": 0}], "cb": 0, "zyx": [2, 45, 69], "corr_l2r": 0.021469156235197785}