{"p": 0.5688, "rgb": "#67809b", "corr": -0.02153819848476359, "words": [{"color": "#12d86d", "text": "formation", "initloc": {"y": 0, "x": 0}, "size": 0}, {"color": "#34ac25", "text": "divided", "initloc": {"y": 0, "x": 0}, "size": 0}, {"color": "#379326", "text": "divisions", "initloc": {"y": 0, "x": 0}, "size": 0}, {"color": "#5eb48e", "text": "largely", "initloc": {"y": 0, "x": 0}, "size": 0}, {"color": "#53a38c", "text": "significant", "initloc": {"y": 0, "x": 0}, "size": 0}, {"color": "#557b7d", "text": "strategic", "initloc": {"y": 0, "x": 0}, "size": 0}, {"color": "#12ca8d", "text": "rapid", "initloc": {"y": 0, "x": 0}, "size": 0}, {"color": "#11b987", "text": "continuous", "initloc": {"y": 0, "x": 0}, "size": 0}, {"color": "#a4884c", "text": "territory", "initloc": {"y": 0, "x": 0}, "size": 0}, {"color": "#5d7349", "text": "maintained", "initloc": {"y": 0, "x": 0}, "size": 0}, {"color": "#947d3c", "text": "territories", "initloc": {"y": 0, "x": 0}, "size": 0}, {"color": "#229d5b", "text": "extensive", "initloc": {"y": 0, "x": 0}, "size": 0}, {"color": "#4bb495", "text": "greater", "initloc": {"y": 0, "x": 0}, "size": 0}, {"color": "#5bab67", "text": "considerable", "initloc": {"y": 0, "x": 0}, "size": 0}, {"color": "#0ca99f", "text": "structures", "initloc": {"y": 0, "x": 0}, "size": 0}, {"color": "#49708d", "text": "foundations", "initloc": {"y": 0, "x": 0}, "size": 0}, {"color": "#46b311", "text": "estimated", "initloc": {"y": 0, "x": 0}, "size": 0}, {"color": "#32bd51", "text": "region", "initloc": {"y": 0, "x": 0}, "size": 0}, {"color": "#735b4b", "text": "conducted", "initloc": {"y": 0, "x": 0}, "size": 0}, {"color": "#7f8775", "text": "consequently", "initloc": {"y": 0, "x": 0}, "size": 0}], "cb": 0, "zyx": [24, 80, 59], "corr_l2r": -0.07085513010288381}