{"p": 0.2123, "rgb": "#ff85ff", "corr": 0.05771678661318516, "words": [{"color": "#fe37ff", "text": "remark", "initloc": {"y": 0, "x": 0}, "size": 4}, {"color": "#b73cc6", "text": "shouting", "initloc": {"y": 0, "x": 0}, "size": 4}, {"color": "#ff1fdb", "text": "hysterical", "initloc": {"y": 0, "x": 0}, "size": 4}, {"color": "#fc77a7", "text": "repeatedly", "initloc": {"y": 0, "x": 0}, "size": 4}, {"color": "#fd00c0", "text": "spoke", "initloc": {"y": 0, "x": 0}, "size": 4}, {"color": "#ef4977", "text": "younger", "initloc": {"y": 0, "x": 0}, "size": 4}, {"color": "#ca57ab", "text": "chap", "initloc": {"y": 0, "x": 0}, "size": 4}, {"color": "#f010b8", "text": "kindly", "initloc": {"y": 0, "x": 0}, "size": 4}, {"color": "#ff58db", "text": "acting", "initloc": {"y": 0, "x": 0}, "size": 3}, {"color": "#e20060", "text": "asked", "initloc": {"y": 0, "x": 0}, "size": 3}, {"color": "#ff4a9c", "text": "sarah", "initloc": {"y": 0, "x": 0}, "size": 3}, {"color": "#ff1062", "text": "sister", "initloc": {"y": 0, "x": 0}, "size": 3}, {"color": "#ff3199", "text": "herself", "initloc": {"y": 0, "x": 0}, "size": 3}, {"color": "#ff2fae", "text": "acted", "initloc": {"y": 0, "x": 0}, "size": 3}, {"color": "#ed2f5b", "text": "sister's", "initloc": {"y": 0, "x": 0}, "size": 3}, {"color": "#c91173", "text": "teacher", "initloc": {"y": 0, "x": 0}, "size": 3}, {"color": "#f30fca", "text": "ignored", "initloc": {"y": 0, "x": 0}, "size": 3}, {"color": "#ee5bb0", "text": "foreigner", "initloc": {"y": 0, "x": 0}, "size": 3}, {"color": "#be66e3", "text": "imaginary", "initloc": {"y": 0, "x": 0}, "size": 3}, {"color": "#bc2cb9", "text": "taught", "initloc": {"y": 0, "x": 0}, "size": 3}], "cb": 0, "zyx": [16, 18, 46], "corr_l2r": 0.15282750764251304}