{"p": 0.7345, "rgb": "#687f9a", "corr": -0.03601190386844906, "words": [{"color": "#6e8006", "text": "march", "initloc": {"y": 0, "x": 0}, "size": 0}, {"color": "#6c7f09", "text": "october", "initloc": {"y": 0, "x": 0}, "size": 0}, {"color": "#677c0a", "text": "september", "initloc": {"y": 0, "x": 0}, "size": 0}, {"color": "#707e06", "text": "july", "initloc": {"y": 0, "x": 0}, "size": 0}, {"color": "#757a09", "text": "april", "initloc": {"y": 0, "x": 0}, "size": 0}, {"color": "#737a08", "text": "june", "initloc": {"y": 0, "x": 0}, "size": 0}, {"color": "#6e7302", "text": "december", "initloc": {"y": 0, "x": 0}, "size": 0}, {"color": "#708105", "text": "february", "initloc": {"y": 0, "x": 0}, "size": 0}, {"color": "#6b7411", "text": "york", "initloc": {"y": 0, "x": 0}, "size": 0}, {"color": "#697a09", "text": "august", "initloc": {"y": 0, "x": 0}, "size": 0}, {"color": "#6d7b04", "text": "november", "initloc": {"y": 0, "x": 0}, "size": 0}, {"color": "#697900", "text": "january", "initloc": {"y": 0, "x": 0}, "size": 0}, {"color": "#a78c40", "text": "james", "initloc": {"y": 0, "x": 0}, "size": 0}, {"color": "#71833e", "text": "led", "initloc": {"y": 0, "x": 0}, "size": 0}, {"color": "#8e8443", "text": "martin", "initloc": {"y": 0, "x": 0}, "size": 0}, {"color": "#345800", "text": "hall", "initloc": {"y": 0, "x": 0}, "size": 0}, {"color": "#773315", "text": "entered", "initloc": {"y": 0, "x": 0}, "size": 0}, {"color": "#868f42", "text": "wilson", "initloc": {"y": 0, "x": 0}, "size": 0}, {"color": "#4e7800", "text": "th", "initloc": {"y": 0, "x": 0}, "size": 0}, {"color": "#786930", "text": "joined", "initloc": {"y": 0, "x": 0}, "size": 0}], "cb": 0, "zyx": [18, 51, 51], "corr_l2r": 0.04499608040615088}