{"p": 0.402, "rgb": "#60829a", "corr": 0.012589411617014384, "words": [{"color": "#556310", "text": "headquarters", "initloc": {"y": 0, "x": 0}, "size": 0}, {"color": "#717136", "text": "massachusetts", "initloc": {"y": 0, "x": 0}, "size": 0}, {"color": "#398d15", "text": "city's", "initloc": {"y": 0, "x": 0}, "size": 0}, {"color": "#16a438", "text": "southwest", "initloc": {"y": 0, "x": 0}, "size": 0}, {"color": "#359647", "text": "atlantic", "initloc": {"y": 0, "x": 0}, "size": 0}, {"color": "#4c7434", "text": "neighboring", "initloc": {"y": 0, "x": 0}, "size": 0}, {"color": "#299332", "text": "pacific", "initloc": {"y": 0, "x": 0}, "size": 0}, {"color": "#5b823f", "text": "corps", "initloc": {"y": 0, "x": 0}, "size": 0}, {"color": "#657f32", "text": "established", "initloc": {"y": 0, "x": 0}, "size": 0}, {"color": "#616e47", "text": "institute", "initloc": {"y": 0, "x": 0}, "size": 0}, {"color": "#707c34", "text": "virginia", "initloc": {"y": 0, "x": 0}, "size": 0}, {"color": "#6f7e14", "text": "hong", "initloc": {"y": 0, "x": 0}, "size": 0}, {"color": "#58853e", "text": "georgia", "initloc": {"y": 0, "x": 0}, "size": 0}, {"color": "#5d7838", "text": "washington", "initloc": {"y": 0, "x": 0}, "size": 0}, {"color": "#3f8d41", "text": "fort", "initloc": {"y": 0, "x": 0}, "size": 0}, {"color": "#1ca33e", "text": "southeast", "initloc": {"y": 0, "x": 0}, "size": 0}, {"color": "#379326", "text": "divisions", "initloc": {"y": 0, "x": 0}, "size": 0}, {"color": "#278f18", "text": "operated", "initloc": {"y": 0, "x": 0}, "size": 0}, {"color": "#558019", "text": "los", "initloc": {"y": 0, "x": 0}, "size": 0}, {"color": "#51715d", "text": "providence", "initloc": {"y": 0, "x": 0}, "size": 0}], "cb": 0, "zyx": [7, 53, 66], "corr_l2r": 0.02739882302236329}