{"p": 0.3324, "rgb": "#5a53ce", "corr": 0.03925581760962246, "words": [{"color": "#da3ad0", "text": "regarding", "initloc": {"y": 0, "x": 0}, "size": 0}, {"color": "#8a63de", "text": "exists", "initloc": {"y": 0, "x": 0}, "size": 0}, {"color": "#a020a6", "text": "future", "initloc": {"y": 0, "x": 0}, "size": 0}, {"color": "#9d2edb", "text": "existence", "initloc": {"y": 0, "x": 0}, "size": 0}, {"color": "#d137ba", "text": "concerning", "initloc": {"y": 0, "x": 0}, "size": 0}, {"color": "#8461f2", "text": "scientific", "initloc": {"y": 0, "x": 0}, "size": 0}, {"color": "#c435a7", "text": "seeking", "initloc": {"y": 0, "x": 0}, "size": 0}, {"color": "#837cff", "text": "nature", "initloc": {"y": 0, "x": 0}, "size": 0}, {"color": "#be39ce", "text": "subject", "initloc": {"y": 0, "x": 0}, "size": 0}, {"color": "#5d69df", "text": "concept", "initloc": {"y": 0, "x": 0}, "size": 0}, {"color": "#9836ff", "text": "understanding", "initloc": {"y": 0, "x": 0}, "size": 0}, {"color": "#ea5fff", "text": "belief", "initloc": {"y": 0, "x": 0}, "size": 0}, {"color": "#bc4ac3", "text": "conception", "initloc": {"y": 0, "x": 0}, "size": 0}, {"color": "#996be4", "text": "exist", "initloc": {"y": 0, "x": 0}, "size": 0}, {"color": "#a830e6", "text": "spiritual", "initloc": {"y": 0, "x": 0}, "size": 0}, {"color": "#bf69f1", "text": "interpretation", "initloc": {"y": 0, "x": 0}, "size": 0}, {"color": "#e03fff", "text": "expressing", "initloc": {"y": 0, "x": 0}, "size": 0}, {"color": "#a3979c", "text": "therefore", "initloc": {"y": 0, "x": 0}, "size": 0}, {"color": "#656ba2", "text": "research", "initloc": {"y": 0, "x": 0}, "size": 0}, {"color": "#c673cd", "text": "biological", "initloc": {"y": 0, "x": 0}, "size": 0}], "cb": 0, "zyx": [13, 49, 28], "corr_l2r": 0.24906035143633942}